storysniffer/__init__.py
storysniffer/path-and-text-model.skops
storysniffer/path-only-model.skops
storysniffer-1.0.7.dist-info/LICENSE
storysniffer-1.0.7.dist-info/METADATA
storysniffer-1.0.7.dist-info/WHEEL
storysniffer-1.0.7.dist-info/top_level.txt
storysniffer-1.0.7.dist-info/RECORD
