Metadata-Version: 2.1
Name: storysniffer
Version: 1.0.7
Summary: Inspect a URL and estimate if it contains a news story
Home-page: https://palewi.re/docs/storysniffer/
Author: Ben Welsh
Author-email: b@palewi.re
License: MIT
Project-URL: Documentation, https://palewi.re/docs/storysniffer/
Project-URL: Source, https://github.com/palewire/storysniffer/
Project-URL: Tracker, https://github.com/palewire/storysniffer/issues
Classifier: Development Status :: 5 - Production/Stable
Classifier: Intended Audience :: Developers
Classifier: Intended Audience :: Science/Research
Classifier: License :: OSI Approved :: MIT License
Classifier: Operating System :: OS Independent
Classifier: Programming Language :: Python
Classifier: Programming Language :: Python :: 3
Classifier: Programming Language :: Python :: 3.9
Classifier: Programming Language :: Python :: 3.10
Classifier: Programming Language :: Python :: 3.11
Classifier: Topic :: Software Development :: Libraries :: Python Modules
License-File: LICENSE
Requires-Dist: tldextract
Requires-Dist: scikit-learn
Requires-Dist: skops
Requires-Dist: pandas
